{
    "file": "do20240503p01_extrato_contrato_411.md",
    "context": "EXTRATO DE CONTRATO Nº DO DOCUMENTO 22001039691/2024 40 IG 1310079 CONTRATANTE: O Estado do Ceará, através da Secretaria da Educação/EEMTI JENNY GOMES - Município de FORTALEZA/CE, inscrita no CNPJ/MF 07.954.514/0480- 80, neste ato representada por seu(sua) Diretor(a) Geral, Sr.(a) MARCOS ANTONIO BEZERRA COSTA CONTRATADA: DIMAIA’S COMERCIAL LTDA, inscrita no CNPJ sob nº 00.289.070/0001-01, representada neste ato pelo AUGUSTO CÉSAR CARVALHO MAIA. OBJETO: O objeto do presente instrumento é a contratação de MATERIAL DE CONSUMO - GÊNEROS DE ALIMENTAÇÃO, nas condições estabelecidas na Cotação Eletrônica nº 2024/03969 e Termo de Participação nº 20240005, Termo de Referência e na proposta do CONTRATADO. FUNDAMENTAÇÃO LEGAL: .O presente contrato tem como fundamento na Cotação Eletrônica nº 2024/03969 e Termo de Participação nº 20240005, e seus anexos, os preceitos do direito público, no art. 75, II da Lei Federal nº 14.133, de 1º de abril de 2021, a Lei Complementar nº 288 de 20 de julho de 2022, Decreto nº 35.341, de 09 de março de 2023, alterado pelo Decreto nº 35.474, de 26 de maio de 2023, Decreto Estadual nº 35.322, de 24 de fevereiro de 2023, alterado pelo Decreto Estadual nº 35.475, de 26 de maio de 2023, e demais legislações aplicáveis ao cumprimento de seu objeto FORO: FORTALEZA/CE. VIGÊNCIA: O prazo de vigência do contrato é de 365 (trezentos e sessenta e cinco) dias, contado do(a) publicação, na forma do art. 105 c/c o art. 94 ambos da Lei n° 14.133/2021, admitindo-se a sua prorrogação desde que a autoridade competente ateste que as condições e os preços permanecem vantajosos para a Administração, permitida a negociação com o CONTRATADO. O PRAZO DE EXECUÇÃO O prazo de execução do objeto contratual é de 300 (trezentos) dias, contado a partir do recebimento da primeira ordem de fornecimento ou instrumento equivalente. VALOR GLOBAL: R$ 19.560,00 (dezenove mil e quinhentos e sessenta reais) pagos em CONFORMIDADE COM O CONTRATO ORIGINAL DOTAÇÃO ORÇAMENTÁRIA: 22100022.12.362.144.20974.03.3390 30.50000.0 – 1257. DATA DA ASSINATURA: 11 de Abril de 2024 SIGNATÁRIOS: CONTRATANTE - MARCOS ANTONIO BEZERRA COSTA CONTRATADA - AUGUSTO CÉSAR CARVALHO MAIA e TESTEMUNHAS: 1 - ANTONIA VALDIANA FERNANDES OLIVEIRA HONORATO 2 - IZAC DALVA MONTENEGRO FERNANDES FILHO, Fortaleza 29 de abril de 2024. Marcos Felipe Vicente COORDENADOR/ASJUR *** *** ***",
    "question": "Qual o cargo do servidor que autenticou o contrato?",
    "answer": "COORDENADOR/ASJUR",
    "answer_start": 2340,
    "is_impossible": false
}