{
    "file": "do20240605p01_extrato_contrato_766.md",
    "context": "EXTRATO DE CONTRATO Nº DO DOCUMENTO 22001076427/2024 97 IG 1317230 CONTRATANTE: EEMTI ALDA FERRER AUGUSTO DUTRA - CREDE 17 - Município de LAVRAS DA MANGABEIRA/CE, inscrita no CNPJ sob nº 07.954.514/0648-75, neste ato representada por seu(sua) Diretor(a) Geral, Sr.(a) TEREZA IVONE LOBO PINHEIRO GURGEL CONTRATADA: M.G.C. DE ALMEIDA GOMES, inscrita no CNPJ sob nº 53.066.849/0001-24, doravante denominado CONTRATADO, representado neste ato pelo MARFISA GABRIELLA CORREIA DE ALMEIDA GOMES. OBJETO: O objeto do presente instrumento é a contratação de aquisição de Gêneros Alimentícios, Lote 03 frutas, verduras e legumes; ovos, leites e laticínios; bebidas não alcoólicas; açúcar e artigos para confeitaria e óleo e gorduras vegetais, nas condições estabelecidas na Cotação Eletrônica nº 2024/08019, Termo de Participação nº 09/2024, Termo de Referência e na proposta do CONTRATADO. FUNDA- MENTAÇÃO LEGAL: O presente contrato tem como fundamento na Cotação Eletrônica nº 2024/08019 e Termo de Participação nº 09/2024, e seus anexos, os preceitos do direito público, no art. 75, II da Lei Federal nº 14.133, de 1º de abril de 2021, a Lei Complementar nº 288, de 20 de julho de 2022, Decreto nº 35.341, de 09 de março de 2023, alterado pelo Decreto nº 35.474, de 26 de maio de 2023, Decreto Estadual nº 35.322, de 24 de fevereiro de 2023, alterado pelo Decreto Estadual nº 35.475, de 26 de maio de 2023, e demais legislações aplicáveis ao cumprimento de seu objeto FORO: LAVRAS DA MANGA- BEIRA/CE. VIGÊNCIA: O prazo de vigência do contrato é de 360 (trezentos e sessenta) dias, contado do(a) publicação, na forma do art. 105 c/c o art. 94 ambos da Lei n° 14.133/2021, admitindo-se a sua prorrogação desde que a autoridade competente ateste que as condições e os preços permanecem vantajosos para a Administração, permitida a negociação com o CONTRATADO. O PRAZO DE EXECUÇÃO O prazo de execução do objeto contratual é de 360 (trezentos e sessenta), contado a partir do recebimento da primeira ordem de fornecimento ou instrumento equivalente. VALOR GLOBAL: R$ 1.494,00 (mil quatrocentos e noventa quatro reais) pagos em CONFORMIDADE COM O CONTRATO ORIGINAL DOTAÇÃO ORÇAMENTÁRIA: 22100022.12.36 2.144.20974.01.339030.50000.0 - 8835. DATA DA ASSINATURA: 24 de Maio de 2024 SIGNATÁRIOS: CONTRATANTE - TEREZA IVONE LOBO PINHEIRO GURGEL CONTRATADA - MARFISA GABRIELLA CORREIA DE ALMEIDA GOMES e TESTEMUNHAS: 1 - JAKELINE GONCALVES DE OLIVEIRA 2 - MARFISA GABRIELLA CORREIA DE ALMEIDA GOMES, Fortaleza 29 de maio de 2024. Marcos Felipe Vicente COORDENADOR/ASJUR ---",
    "question": "Qual é o nome do signatário associado ao CONTRATANTE?",
    "answer": "TEREZA IVONE LOBO PINHEIRO GURGEL",
    "answer_start": 268,
    "is_impossible": false
}