{
    "file": "do20240618p01_extrato_contrato_956.md",
    "context": "EXTRATO DE CONTRATO Nº DO DOCUMENTO Nº54/2024/NUP 22001.034755/2023-35 IG: 1321489 SACC:1320051 CONTRATANTE: O ESTADO DO CEARÁ, por intermédio da SECRETARIA DA EDUCAÇÃO, situada(o) no Centro Administrativo Governador Virgílio Távora, na Av. Gal. Afonso Albuquerque Lima, s/n, Cambeba, Fortaleza - CE, inscrita(o) no CNPJ sob o Nº 07.954.514/0001-25, doravante denominada CONTRATANTE, neste ato representada pela Sra. ELIANA NUNES ESTRELA, Secretária da Educação, brasileira, inscrita no CPF sob o nº 473400533-87, RG nº 216562291 SSP CE, residente e domiciliada em Fortaleza/CE, residente e domiciliado em Fortaleza/CE, CONTRATADA: EMPRESA FC ALVES DA SILVA EMBALAGENS- ME, estabelecida na Rua Governador Sampaio, nº126, Centro – Fortaleza – Ceará , CEP: 60.055-050, inscrita no CNPJ sob o nº 11.372.526/0001-19, doravante denominada CONTRATADA, representada neste ato pelo Sr. FRANCISCO CARLOS ALVES DA SILVA, RG 98012029247 SSP-CE e inscrito no CPF sob nº 683.875.123-20, têm entre si justa e acordada a celebração do presente contrato, mediante as cláusulas e condições seguintes: . OBJETO: 3.1. Constitui objeto deste contrato Serviço de manutenção predial com reformas das paredes, pisos, reposição de peças e com coleta, transporte e destino final de resíduos sólidos classe B, a fim de atender a demanda contratual da secretaria da educação do Estado, de acordo com as especificações e quantitativos previstos no Termo de Referência. FUNDAMENTAÇÃO LEGAL: 1.1.O presente contrato tem como fundamento o edital da Cotação Eletrônica nº 2024/05925, Termo de Participação nº 20240047, e seus anexos, os preceitos do direito público, a Lei Federal nº º 14.133, de 1º de abril de 2021, e outras leis especiais necessárias ao cumprimento de seu objeto FORO: Fortaleza/ce. VIGÊNCIA: 8.1. O prazo de vigência contratual poderá ser de 06 (seis) meses, contado a partir da sua publicação. 8.1.1. A publicação resumida do instrumento de contrato dar-se-á na forma da Lei Federal nº 14.133/21. 8.2. O prazo de execução do objeto contratual poderá ser de 05 (cinco. VALOR GLOBAL: R$ R$ 42.688,47 O preço contratual global importa na quantia de R$ 42.688,47 (quarenta e dois mil, seiscentos e oitenta e oito reais e quarenta e sete centavos) . pagos em DOTAÇÃO ORÇAMENTÁRIA: As despesas decorrentes da contratação serão provenientes dos recursos: Funcional Programática 22100022.12.122.421.20168.15.339039.1.5009100 000.0. DATA DA ASSINATURA: 26 de Abril de 2024. SIGNATÁRIOS: ELIANA NUNES ESTRELA CONTRATANTE FRANCISCO CARLOS ALVES DA SILVA CONTRATADA e TESTEMUNHAS: 1. SANDRA MARIA RODRIGUES 2. ANNA DAISY SOARES BENEVIDES Fortaleza, 12 de junho de 2024. Ana Talita Ferreira Alves COORDENADORA ASJUR *** *** ***",
    "question": "Qual é o valor global do contrato em reais?",
    "answer": "R$ 42.688,47",
    "answer_start": 2075,
    "is_impossible": false
}