{
    "file": "do20240523p01_extrato_contrato_614.md",
    "context": "EXTRATO DE CONTRATO Nº DO DOCUMENTO 22001.033544/2024-66 - IG: 1312356 CONTRATANTE: O Estado do Ceará, através da Secretaria da Educação/ESCOLA EEEP PROFESSORA ROSÂNGELA ALBUQUERQUE DE COUTO, estabelecida ao CONJUNTO INDUSTRIAL, nº 01, Bairro CENTRO, Município de ITAREMA/CE, CEP 62.590-000 Telefone (88) 3667-1661, inscrita no CNPJ/MF 07.954.514/0792-01, daqui por diante denominada simplesmente CONTRATANTE neste ato representada por seu (sua) Diretor (a) Geral, Sr.(a) José Ivaldo Bleasby Freires CONTRATADA: COOPERATIVA DOS PRODUTORES AGRÍCOLAS E PECUARISTAS DO VALE DO ACARAÚ, situada na VILA TUCUNZEIROS, S/N,Bairro ZONA RURAL, município ACARAÚ/CE, CEP 62.580-000 inscrita no CNPJ sob n.º 33.029.345/0001-27, representado neste ato pelo(a) Sr.(a) Carlos Alberto Cordeiro. OBJETO: É objeto desta contratação a aquisição de GÊNEROS ALIMENTÍCIOS DA AGRICULTURA FAMILIAR PARA ALIMENTAÇÃO ESCOLAR, aos alunos da rede de educação básica pública, verba FNDE/PNAE, descritos no quadro previsto na Cláusula Quarta, todos de acordo com a chamada pública nº 20240001, o qual fica fazendo parte integrante do presente contrato, independente- mente de anexação ou transcrição. FUNDAMENTAÇÃO LEGAL: fundamentados nas disposições da Lei nº 11.947/2009, e tendo em vista o que consta na Chamada Pública nº 20240001 FORO: Itarema/CE. VIGÊNCIA: E EXECUÇÃO: O prazo de vigência e de execução deste contrato será de 365 (Trezentos e sessenta e cinco) dias, contados a partir da data de publicação em D.O.E. VALOR GLOBAL: R$ 107.610,38 (Cento e sete mil, seiscentos e dez reais e trinta e oito centavos) pagos em conformidade com o contrato original. DOTAÇÃO ORÇAMENTÁRIA: 22100022.12.362.231.20979.05.339030.50000.0-4929 do PROGRAMA DE ALIMENTAÇÃO ESCOLAR – PNAE. DATA DA ASSINATURA: 15 de Maio de 2024. SIGNATÁRIOS: José Ivaldo Bleasby Freires - CONTRATANTE – Carlos Alberto Cordeiro – CONTRATADA e TESTEMUNHAS: 01- ILEGÍVEL, 02- ILEGÍVEL. Fortaleza, 21 de maio de 2024. Marcos Felipe Vicente COORDENADOR/ASJUR *** *** ***",
    "question": "Qual é o valor global do contrato em reais?",
    "answer": "R$ 107.610,38",
    "answer_start": 1507,
    "is_impossible": false
}