{
    "file": "do20240529p01_extrato_contrato_720.md",
    "context": "EXTRATO DE CONTRATO Nº DO DOCUMENTO 22001057855/202411 - IG - 1315683 CONTRATANTE: O Estado do Ceará, através da Secretaria da Educação/EEMTI MAURO SAMPAIO, estabelecida à Rua Major Januário, S/N, Bairro Centro, Município de Barro-CE, CEP 63.380-000 Telefone (88) 3554-1547, inscrita no CNPJ/MF 07.954.514/059-65 daqui por diante denominada simples- mente CONTRATANTE neste ato representada por seu Diretor Geral, Sr. Francisco Edson Pereira Ferreira CONTRATADA: COOPERATIVA DE AGRI- CULTORES FAMILIARES DO CENTRO SUL - COOPERCENTRO, situada no Sítio Carnaubinha, n.º 25895, Zona Rural, município de Quixelô-CE, CEP: 63.515-000 inscrita no CNPJ sob n.º 32.144.817/0001-20, representada neste ato pelo(a)Sr.(a) Lucivan José Vieira da Silva. OBJETO: objeto desta contratação a aquisição de GÊNEROS ALIMENTÍCIOS DA AGRICULTURA FAMILIAR PARA ALIMENTAÇÃO ESCOLAR, aos alunos da rede de educação básica pública, verba FNDE/PNAE, descritos no quadro previsto na Cláusula Quarta, todos de acordo com a chamada pública nº 2024/001, o qual fica fazendo parte integrante do presente contrato, independentemente de anexação ou transcrição. FUNDAMENTAÇÃO LEGAL: fundamentados nas disposiçõesda Lei nº 11.947/2009, da Lei Federal nº 14.133/2021, Lei Federal nº 14.660/2023 e demais Legislação relativas ao PNAE, inclusive a Resolução 06/2020 e suas alterações, e tendo em vista o que consta na Chamada Pública nº 2024/001, resolvem celebrar o presente contrato mediante as cláusulas que seguem FORO: BARRO/CE. VIGÊNCIA: O prazo de vigência e de execução deste contrato será de 365 ( Trezentos e Sessenta e Cinco Dias) dias, contados a partir da data de publicação em D.O.E. VALOR GLOBAL: R$ 98.468,81 (Noventa e Oito Mil, Quatrocentos e Sessenta e Oito Reais, Oitenta e Um Centavos) pagos em conformidade com o contrato original DOTAÇÃO ORÇAMENTÁRIA: 22100022.12.362.144.20974.01.339030.50000.0 - 8835 do PROGRAMA DE ALIMENTAÇÃO ESCOLAR – PNAE. DATA DA ASSINATURA: 20 de Maio de 2024 SIGNATÁRIOS: Francisco Edson Pereira Ferreira - CONTRATANTE - Lucivan José Vieira da Silva, - CONTRATADA e TESTEMUNHA 01 - Karla Maria dos Santos Caldas - TESTEMUNHA 02 - Josefa Fernanda Rodrigues Correia - Fortaleza, 27 de maio de 2024. Marcos Felipe Vicente COORDENADOR/ASJUR *** *** ***",
    "question": "Qual é o número do IG do documento indicado após 'IG'?",
    "answer": "1315683",
    "answer_start": 62,
    "is_impossible": false
}